{
  "home": "Accueil",
  "login": "Connexion",
  "logout": "Deconnexion",
  "register": "S'enregistrer",
  "name": "Nom",
  "lastname": "Nom de Famille",
  "firstname": "Prénom",
  "email": "E-mail",
  "language": "Language",
  "list": "Liste",
  "modify": "Modifier",
  "add": "Ajouter",
  "selectlanguage": "Sélectionner un langage",
  "waitopinion": "En attente d'avis",
  "mydecisions": "Mes décisions",
  "theformhasbeensubmittedsuccessfully!": "Le formulaire a été soumis avec succès !",
  "backtodecisions": "Revenir aux décisions",
  "description": "Description",
  "describeherealltheinformationconcerningthedescription": "Décrire ici toutes les informations concernant la description",
  "title": "Titre",
  "Thisfieldisrequiredandmustcontainatleast5characters": "Ce champs est requis et doit contenir au moins 5 caractères",
  "usefulnessfortheorganization": "Utilité pour l'organisation",
  "contextaroundthedecision": " Contexte autour de la décision",
  "benefits": "Bénéfices",
  "disadvantages": "Inconvénients",
  "peopleconcerned": "Personnes concernées",
  "designatethepeopleconcerned": " Désigner les personnes concernées (impactées ou expertes) par la décision",
  "": "Calendrier",
  "setdecision-makingtimeline": "Définir le calendrier de la prise de décision",
  "dateoffilingofthedecision": "Date de dépôt de la décision",
  "deadlinetogivefeedback": "Deadline pour donner son avis",
  "thisdatemustbegreaterthanthedateoftoday": " Cette date doit être supérieure à la date d'aujourd'hui",
  "dateofirstdecision": "Date de prise de la première décision",
  "cancel": "Annuler",
  "save": "Sauvegarder",
  "context": "Contexte",
  "avantages": "Avantages",
  "timeline": "Chronologie",
  "decisionmakingstarted": "Prise de décision commencée",
  "deadline": "Deadline pour donner son avis",
  "firstdecision": "Première Décision",
  "": "Les personnes concernées",
  "finaldecision": "Décision final",
  "noonehasbeennamedasimpacted": "Personne n'a été désigné comme étant impacté",
  "noonehasbeenappointedasanexpert": "Personne n'a été désigné expert",
  "andothers": "et autres...",
  "thedecisionhasbeenremoved": "La décision a bien été supprimée",
  "backtodecisions": "Revenir aux décisions",
  "author": " Auteur",
  "statut": "Statut",
  "depositdate": " Date de dépôt",
  "edit": "Edite",
  "numberofpersons": "Nombre de personnes",
  "language": "langage",
  "notice": "avis",
  "alldecisions": "Toutes les décisions",
  "awaitingfirstdecision": "En attente première décision",
  "inconflict": "En conflit",
  "archiveddecisions": "Décisions archivées",
  "unsuccessfuldecisions": "Décisions non abouties",
  "fileadecision": "Déposer une décision",
  "describealltheelementsofhisdecision": "Décrire tous les éléments de sa décision",
  "setschedule": "Définir le calendrier",
  "endoftakingopinions": "Fin de la prise des avis",
  "thisdatemustbegreaterthantodaysdate": " Cette date doit être supérieure à la date d'aujourd'hui.",
  "endofthefirstdecision": "Fin de la première décision",
  "endoftheconflictonthefirstdecision": "Fin du conflit sur la première décision",
  "postmydecision": "Poster ma décision",
  "through": "Par",
  "therewasanerrorloadingthecomponent!": "Il y a eu une erreur lors du chargement du composant !",
  "madebymakesense": "Réalisé par makesens",
  "groupsconcerned": "Groupes concernés",
  "groupsimpacted": "Groupes impactés",
  "groupsexperts": "Groupes experts"
}
